sentry/__init__.py
sentry/__main__.py
sentry/admin.py
sentry/app.py
sentry/assets.json
sentry/celery.py
sentry/constants.py
sentry/coreapi.py
sentry/django_admin.py
sentry/event_manager.py
sentry/exceptions.py
sentry/http.py
sentry/signals.py
sentry/wsgi.py
sentry/api/__init__.py
sentry/api/authentication.py
sentry/api/base.py
sentry/api/client.py
sentry/api/decorators.py
sentry/api/exceptions.py
sentry/api/paginator.py
sentry/api/permissions.py
sentry/api/urls.py
sentry/api/bases/__init__.py
sentry/api/bases/group.py
sentry/api/bases/organization.py
sentry/api/bases/organizationissues.py
sentry/api/bases/organizationmember.py
sentry/api/bases/project.py
sentry/api/bases/team.py
sentry/api/bases/user.py
sentry/api/endpoints/__init__.py
sentry/api/endpoints/api_tokens.py
sentry/api/endpoints/auth_index.py
sentry/api/endpoints/broadcast_index.py
sentry/api/endpoints/catchall.py
sentry/api/endpoints/dsym_files.py
sentry/api/endpoints/event_details.py
sentry/api/endpoints/group_details.py
sentry/api/endpoints/group_environment_details.py
sentry/api/endpoints/group_events.py
sentry/api/endpoints/group_events_latest.py
sentry/api/endpoints/group_events_oldest.py
sentry/api/endpoints/group_hashes.py
sentry/api/endpoints/group_notes.py
sentry/api/endpoints/group_notes_details.py
sentry/api/endpoints/group_participants.py
sentry/api/endpoints/group_stats.py
sentry/api/endpoints/group_tagkey_details.py
sentry/api/endpoints/group_tagkey_values.py
sentry/api/endpoints/group_tags.py
sentry/api/endpoints/group_user_reports.py
sentry/api/endpoints/index.py
sentry/api/endpoints/internal_stats.py
sentry/api/endpoints/legacy_project_redirect.py
sentry/api/endpoints/organization_access_request_details.py
sentry/api/endpoints/organization_activity.py
sentry/api/endpoints/organization_auditlogs.py
sentry/api/endpoints/organization_details.py
sentry/api/endpoints/organization_index.py
sentry-8.10.0.dist-info/DESCRIPTION.rst
sentry-8.10.0.dist-info/METADATA
sentry-8.10.0.dist-info/RECORD
sentry-8.10.0.dist-info/WHEEL
sentry-8.10.0.dist-info/entry_points.txt
sentry-8.10.0.dist-info/metadata.json
sentry-8.10.0.dist-info/top_level.txt
